rust_reversi-1.4.4.dist-info/METADATA
rust_reversi-1.4.4.dist-info/WHEEL
rust_reversi-1.4.4.dist-info/licenses/LICENSE.txt
rust_reversi/__init__.py
rust_reversi/__init__.pyi
rust_reversi/py.typed
rust_reversi/rust_reversi.cpython-312-darwin.so
rust_reversi-1.4.4.dist-info/RECORD
