Metadata-Version: 2.4
Name: rust-reversi
Version: 1.4.4
Classifier: Programming Language :: Rust
Classifier: Programming Language :: Python :: Implementation :: CPython
Classifier: Programming Language :: Python :: Implementation :: PyPy
License-File: LICENSE.txt
Summary: A Reversi/Othello engine implemented in Rust with Python bindings
Keywords: game,reversi,othello,rust
Author: neodymium6
License: MIT
Requires-Python: >=3.8
Project-URL: Homepage, https://github.com/neodymium6/rust_reversi
Project-URL: Repository, https://github.com/neodymium6/rust_reversi.git
